[
    {
        "id": "abraham-moss",
        "name": "Abraham Moss"
    },
    {
        "id": "altrincham",
        "name": "Altrincham"
    },
    {
        "id": "anchorage",
        "name": "Anchorage"
    },
    {
        "id": "ashton-moss",
        "name": "Ashton Moss"
    },
    {
        "id": "ashton-west",
        "name": "Ashton West"
    },
    {
        "id": "ashton-under-lyne",
        "name": "Ashton-Under-Lyne"
    },
    {
        "id": "audenshaw",
        "name": "Audenshaw"
    },
    {
        "id": "baguley",
        "name": "Baguley"
    },
    {
        "id": "barlow-moor-road",
        "name": "Barlow Moor Road"
    },
    {
        "id": "benchill",
        "name": "Benchill"
    },
    {
        "id": "besses-o-th-barn",
        "name": "Besses o' th' Barn"
    },
    {
        "id": "bowker-vale",
        "name": "Bowker Vale"
    },
    {
        "id": "broadway",
        "name": "Broadway"
    },
    {
        "id": "brooklands",
        "name": "Brooklands"
    },
    {
        "id": "burton-road",
        "name": "Burton Road"
    },
    {
        "id": "bury",
        "name": "Bury"
    },
    {
        "id": "cemetery-road",
        "name": "Cemetery Road"
    },
    {
        "id": "central-park",
        "name": "Central Park"
    },
    {
        "id": "chorlton",
        "name": "Chorlton"
    },
    {
        "id": "clayton-hall",
        "name": "Clayton Hall"
    },
    {
        "id": "cornbrook",
        "name": "Cornbrook"
    },
    {
        "id": "crossacres",
        "name": "Crossacres"
    },
    {
        "id": "crumpsall",
        "name": "Crumpsall"
    },
    {
        "id": "dane-road",
        "name": "Dane Road"
    },
    {
        "id": "deansgate-castlefield",
        "name": "Deansgate-Castlefield"
    },
    {
        "id": "derker",
        "name": "Derker"
    },
    {
        "id": "didsbury-village",
        "name": "Didsbury Village"
    },
    {
        "id": "droylsden",
        "name": "Droylsden"
    },
    {
        "id": "east-didsbury",
        "name": "East Didsbury"
    },
    {
        "id": "eccles",
        "name": "Eccles"
    },
    {
        "id": "edge-lane",
        "name": "Edge Lane"
    },
    {
        "id": "etihad-campus",
        "name": "Etihad Campus"
    },
    {
        "id": "exchange-quay",
        "name": "Exchange Quay"
    },
    {
        "id": "exchange-square",
        "name": "Exchange Square"
    },
    {
        "id": "failsworth",
        "name": "Failsworth"
    },
    {
        "id": "firswood",
        "name": "Firswood"
    },
    {
        "id": "freehold",
        "name": "Freehold"
    },
    {
        "id": "martinscroft",
        "name": "Martinscroft"
    },
    {
        "id": "old-trafford",
        "name": "Old Trafford"
    },
    {
        "id": "radcliffe",
        "name": "Radcliffe"
    },
    {
        "id": "salford-quays",
        "name": "Salford Quays"
    },
    {
        "id": "stretford",
        "name": "Stretford"
    },
    {
        "id": "trafford-bar",
        "name": "Trafford Bar"
    },
    {
        "id": "kingsway-business-park",
        "name": "Kingsway Business Park"
    },
    {
        "id": "langworthy",
        "name": "Langworthy"
    },
    {
        "id": "navigation-road",
        "name": "Navigation Road"
    },
    {
        "id": "harbour-city",
        "name": "Harbour City"
    },
    {
        "id": "heaton-park",
        "name": "Heaton Park"
    },
    {
        "id": "hollinwood",
        "name": "Hollinwood"
    },
    {
        "id": "holt-town",
        "name": "Holt Town"
    },
    {
        "id": "market-street",
        "name": "Market Street"
    },
    {
        "id": "mediacityuk",
        "name": "MediaCityUK"
    },
    {
        "id": "oldham-king-street",
        "name": "Oldham King Street"
    },
    {
        "id": "ladywell",
        "name": "Ladywell"
    },
    {
        "id": "manchester-airport",
        "name": "Manchester Airport"
    },
    {
        "id": "milnrow",
        "name": "Milnrow"
    },
    {
        "id": "monsall",
        "name": "Monsall"
    },
    {
        "id": "moor-road",
        "name": "Moor Road"
    },
    {
        "id": "new-islington",
        "name": "New Islington"
    },
    {
        "id": "newbold",
        "name": "Newbold"
    },
    {
        "id": "newhey",
        "name": "Newhey"
    },
    {
        "id": "newton-heath-and-moston",
        "name": "Newton Heath and Moston"
    },
    {
        "id": "northern-moor",
        "name": "Northern Moor"
    },
    {
        "id": "oldham-central",
        "name": "Oldham Central"
    },
    {
        "id": "oldham-mumps",
        "name": "Oldham Mumps"
    },
    {
        "id": "peel-hall",
        "name": "Peel Hall"
    },
    {
        "id": "piccadilly-gardens",
        "name": "Piccadilly Gardens"
    },
    {
        "id": "piccadilly",
        "name": "Piccadilly"
    },
    {
        "id": "pomona",
        "name": "Pomona"
    },
    {
        "id": "prestwich",
        "name": "Prestwich"
    },
    {
        "id": "queens-road",
        "name": "Queens Road"
    },
    {
        "id": "st-peters-square",
        "name": "St Peter's Square"
    },
    {
        "id": "robinswood-road",
        "name": "Robinswood Road"
    },
    {
        "id": "rochdale-railway-station",
        "name": "Rochdale Railway Station"
    },
    {
        "id": "rochdale-town-centre",
        "name": "Rochdale Town Centre"
    },
    {
        "id": "roundthorn",
        "name": "Roundthorn"
    },
    {
        "id": "sale",
        "name": "Sale"
    },
    {
        "id": "sale-water-park",
        "name": "Sale Water Park"
    },
    {
        "id": "shadowmoss",
        "name": "Shadowmoss"
    },
    {
        "id": "shaw-and-crompton",
        "name": "Shaw & Crompton"
    },
    {
        "id": "shudehill",
        "name": "Shudehill"
    },
    {
        "id": "south-chadderton",
        "name": "South Chadderton"
    },
    {
        "id": "st-werburghs-road",
        "name": "St Werburgh's Road"
    },
    {
        "id": "timperley",
        "name": "Timperley"
    },
    {
        "id": "velopark",
        "name": "Velopark"
    },
    {
        "id": "victoria",
        "name": "Victoria"
    },
    {
        "id": "weaste",
        "name": "Weaste"
    },
    {
        "id": "west-didsbury",
        "name": "West Didsbury"
    },
    {
        "id": "westwood",
        "name": "Westwood"
    },
    {
        "id": "whitefield",
        "name": "Whitefield"
    },
    {
        "id": "withington",
        "name": "Withington"
    },
    {
        "id": "wythenshawe-park",
        "name": "Wythenshawe Park"
    },
    {
        "id": "wythenshawe-town-centre",
        "name": "Wythenshawe Town Centre"
    }
]